{
"meta":{"test_sets":[],"test_metrics":[],"learn_metrics":[{"best_value":"Min","name":"Logloss"}],"launch_mode":"Train","parameters":"","iteration_count":400,"learn_sets":["learn"],"name":"experiment"},
"iterations":[
{"learn":[0.6856974533],"iteration":0,"passed_time":0.004546691032,"remaining_time":1.814129722},
{"learn":[0.6753887942],"iteration":1,"passed_time":0.00916599494,"remaining_time":1.824032993},
{"learn":[0.667972797],"iteration":2,"passed_time":0.01286107541,"remaining_time":1.701948979},
{"learn":[0.6609467465],"iteration":3,"passed_time":0.0189163212,"remaining_time":1.872715798},
{"learn":[0.655215218],"iteration":4,"passed_time":0.02450901533,"remaining_time":1.936212211},
{"learn":[0.648037267],"iteration":5,"passed_time":0.02889186917,"remaining_time":1.897232742},
{"learn":[0.6429318526],"iteration":6,"passed_time":0.03266985064,"remaining_time":1.834178757},
{"learn":[0.6388405287],"iteration":7,"passed_time":0.03688013661,"remaining_time":1.807126694},
{"learn":[0.6333214776],"iteration":8,"passed_time":0.040796847,"remaining_time":1.772396353},
{"learn":[0.6281257936],"iteration":9,"passed_time":0.04449027567,"remaining_time":1.735120751},
{"learn":[0.6227553438],"iteration":10,"passed_time":0.04807831108,"remaining_time":1.70022391},
{"learn":[0.6183497256],"iteration":11,"passed_time":0.05166937584,"remaining_time":1.670643152},
{"learn":[0.6140848273],"iteration":12,"passed_time":0.05485300651,"remaining_time":1.632931809},
{"learn":[0.6068286578],"iteration":13,"passed_time":0.05839337781,"remaining_time":1.609988845},
{"learn":[0.6021271659],"iteration":14,"passed_time":0.06210397521,"remaining_time":1.59400203},
{"learn":[0.5975897173],"iteration":15,"passed_time":0.06532739438,"remaining_time":1.567857465},
{"learn":[0.5923196181],"iteration":16,"passed_time":0.06874677514,"remaining_time":1.548824405},
{"learn":[0.5889283194],"iteration":17,"passed_time":0.07167505368,"remaining_time":1.521103917},
{"learn":[0.5843076119],"iteration":18,"passed_time":0.07470392401,"remaining_time":1.498010266},
{"learn":[0.5774460171],"iteration":19,"passed_time":0.07782282539,"remaining_time":1.478633682},
{"learn":[0.5741059476],"iteration":20,"passed_time":0.08099812034,"remaining_time":1.461823219},
{"learn":[0.5722271929],"iteration":21,"passed_time":0.08425164554,"remaining_time":1.447596455},
{"learn":[0.5678224453],"iteration":22,"passed_time":0.08707351982,"remaining_time":1.427248564},
{"learn":[0.5632978728],"iteration":23,"passed_time":0.0902050343,"remaining_time":1.413212204},
{"learn":[0.5607232626],"iteration":24,"passed_time":0.09280491849,"remaining_time":1.392073777},
{"learn":[0.5583903644],"iteration":25,"passed_time":0.09589283238,"remaining_time":1.379381512},
{"learn":[0.554213353],"iteration":26,"passed_time":0.09857566235,"remaining_time":1.361804521},
{"learn":[0.5508498225],"iteration":27,"passed_time":0.1015301993,"remaining_time":1.348901219},
{"learn":[0.5466571858],"iteration":28,"passed_time":0.1047958706,"remaining_time":1.340664414},
{"learn":[0.5435074615],"iteration":29,"passed_time":0.1076958876,"remaining_time":1.328249281},
{"learn":[0.5406048105],"iteration":30,"passed_time":0.1104141979,"remaining_time":1.31428513},
{"learn":[0.5386323494],"iteration":31,"passed_time":0.1131223348,"remaining_time":1.300906851},
{"learn":[0.5333393391],"iteration":32,"passed_time":0.1159829843,"remaining_time":1.28987137},
{"learn":[0.5305604537],"iteration":33,"passed_time":0.119091809,"remaining_time":1.281988297},
{"learn":[0.5278686304],"iteration":34,"passed_time":0.121749681,"remaining_time":1.269675244},
{"learn":[0.5252685889],"iteration":35,"passed_time":0.1252267617,"remaining_time":1.266181702},
{"learn":[0.5216235271],"iteration":36,"passed_time":0.1280102314,"remaining_time":1.255884163},
{"learn":[0.5186820646],"iteration":37,"passed_time":0.1308089155,"remaining_time":1.246127037},
{"learn":[0.5154549468],"iteration":38,"passed_time":0.1336456415,"remaining_time":1.237078887},
{"learn":[0.5129292289],"iteration":39,"passed_time":0.136827227,"remaining_time":1.231445043},
{"learn":[0.5110542315],"iteration":40,"passed_time":0.1401519795,"remaining_time":1.227184406},
{"learn":[0.5080756531],"iteration":41,"passed_time":0.142832108,"remaining_time":1.217473682},
{"learn":[0.5048147185],"iteration":42,"passed_time":0.1452152612,"remaining_time":1.205624378},
{"learn":[0.5016645819],"iteration":43,"passed_time":0.1475940172,"remaining_time":1.194169776},
{"learn":[0.4971344191],"iteration":44,"passed_time":0.1505433389,"remaining_time":1.187619674},
{"learn":[0.4951205348],"iteration":45,"passed_time":0.1532474767,"remaining_time":1.179339277},
{"learn":[0.4924099702],"iteration":46,"passed_time":0.1555212235,"remaining_time":1.168063658},
{"learn":[0.4891674103],"iteration":47,"passed_time":0.1578064222,"remaining_time":1.157247096},
{"learn":[0.4867874069],"iteration":48,"passed_time":0.1599316545,"remaining_time":1.145632872},
{"learn":[0.4827024522],"iteration":49,"passed_time":0.1620159954,"remaining_time":1.134111968},
{"learn":[0.4810966601],"iteration":50,"passed_time":0.1646137453,"remaining_time":1.126474453},
{"learn":[0.4795670703],"iteration":51,"passed_time":0.1669183841,"remaining_time":1.117069186},
{"learn":[0.4777132429],"iteration":52,"passed_time":0.1690919717,"remaining_time":1.107073853},
{"learn":[0.475080576],"iteration":53,"passed_time":0.1713708271,"remaining_time":1.098042707},
{"learn":[0.4736590807],"iteration":54,"passed_time":0.1734718582,"remaining_time":1.088141656},
{"learn":[0.4704539117],"iteration":55,"passed_time":0.175591348,"remaining_time":1.078632566},
{"learn":[0.4666547957],"iteration":56,"passed_time":0.177733927,"remaining_time":1.069521701},
{"learn":[0.4640427488],"iteration":57,"passed_time":0.1803178725,"remaining_time":1.063253662},
{"learn":[0.4611219063],"iteration":58,"passed_time":0.1827594649,"remaining_time":1.056287755},
{"learn":[0.4593483593],"iteration":59,"passed_time":0.1848674657,"remaining_time":1.047582306},
{"learn":[0.4574617231],"iteration":60,"passed_time":0.1869680659,"remaining_time":1.039052038},
{"learn":[0.4550952373],"iteration":61,"passed_time":0.1894077795,"remaining_time":1.032577895},
{"learn":[0.4523449449],"iteration":62,"passed_time":0.1915550395,"remaining_time":1.024667434},
{"learn":[0.4488914655],"iteration":63,"passed_time":0.1936937776,"remaining_time":1.016892333},
{"learn":[0.446481586],"iteration":64,"passed_time":0.1962414745,"remaining_time":1.011398368},
{"learn":[0.4444725589],"iteration":65,"passed_time":0.198601677,"remaining_time":1.00504485},
{"learn":[0.4433753929],"iteration":66,"passed_time":0.2009370694,"remaining_time":0.9986872256},
{"learn":[0.4413972041],"iteration":67,"passed_time":0.2030099877,"remaining_time":0.9911664104},
{"learn":[0.4404567041],"iteration":68,"passed_time":0.2052430898,"remaining_time":0.9845719233},
{"learn":[0.4380490699],"iteration":69,"passed_time":0.207395312,"remaining_time":0.9777207566},
{"learn":[0.4364763614],"iteration":70,"passed_time":0.2097354979,"remaining_time":0.9718729411},
{"learn":[0.4352454405],"iteration":71,"passed_time":0.2121850663,"remaining_time":0.9666208575},
{"learn":[0.4328059599],"iteration":72,"passed_time":0.2144286679,"remaining_time":0.9605229372},
{"learn":[0.4310479008],"iteration":73,"passed_time":0.2165502925,"remaining_time":0.953991829},
{"learn":[0.4282266757],"iteration":74,"passed_time":0.2185791944,"remaining_time":0.9471765091},
{"learn":[0.4263180449],"iteration":75,"passed_time":0.2206230208,"remaining_time":0.940550773},
{"learn":[0.4253222833],"iteration":76,"passed_time":0.2226702775,"remaining_time":0.934058437},
{"learn":[0.4235741676],"iteration":77,"passed_time":0.2248816893,"remaining_time":0.9283577429},
{"learn":[0.421664712],"iteration":78,"passed_time":0.2271455258,"remaining_time":0.9229584022},
{"learn":[0.4196498655],"iteration":79,"passed_time":0.2291931807,"remaining_time":0.9167727227},
{"learn":[0.415215196],"iteration":80,"passed_time":0.2312651187,"remaining_time":0.9107848503},
{"learn":[0.4134350964],"iteration":81,"passed_time":0.2334352728,"remaining_time":0.9052733751},
{"learn":[0.4109643193],"iteration":82,"passed_time":0.2355483834,"remaining_time":0.8996245485},
{"learn":[0.4083210217],"iteration":83,"passed_time":0.2376661103,"remaining_time":0.8940772719},
{"learn":[0.4068332675],"iteration":84,"passed_time":0.2401604769,"remaining_time":0.8900064731},
{"learn":[0.4052422302],"iteration":85,"passed_time":0.2425597103,"remaining_time":0.8856249889},
{"learn":[0.4029893833],"iteration":86,"passed_time":0.2449048516,"remaining_time":0.8810944662},
{"learn":[0.4010988523],"iteration":87,"passed_time":0.2470647812,"remaining_time":0.8759569514},
{"learn":[0.399585346],"iteration":88,"passed_time":0.2492227847,"remaining_time":0.8708796184},
{"learn":[0.3982729991],"iteration":89,"passed_time":0.2513266481,"remaining_time":0.8656806767},
{"learn":[0.3951241455],"iteration":90,"passed_time":0.2539686965,"remaining_time":0.8623772222},
{"learn":[0.3934694612],"iteration":91,"passed_time":0.2563678005,"remaining_time":0.8582748103},
{"learn":[0.3911423366],"iteration":92,"passed_time":0.258954282,"remaining_time":0.8548275762},
{"learn":[0.3886012682],"iteration":93,"passed_time":0.2613621271,"remaining_time":0.850817137},
{"learn":[0.3857776146],"iteration":94,"passed_time":0.2639685517,"remaining_time":0.8474779816},
{"learn":[0.3844976639],"iteration":95,"passed_time":0.2662008758,"remaining_time":0.8429694401},
{"learn":[0.3827460428],"iteration":96,"passed_time":0.2682507282,"remaining_time":0.8379378416},
{"learn":[0.3805919656],"iteration":97,"passed_time":0.2707146701,"remaining_time":0.8342431671},
{"learn":[0.379012842],"iteration":98,"passed_time":0.2735591194,"remaining_time":0.831730252},
{"learn":[0.3779660804],"iteration":99,"passed_time":0.275718355,"remaining_time":0.827155065},
{"learn":[0.3753968314],"iteration":100,"passed_time":0.2777966864,"remaining_time":0.8223882101},
{"learn":[0.3731254724],"iteration":101,"passed_time":0.280041267,"remaining_time":0.8181597802},
{"learn":[0.3713019792],"iteration":102,"passed_time":0.2822112325,"remaining_time":0.8137547188},
{"learn":[0.3703970143],"iteration":103,"passed_time":0.284386822,"remaining_time":0.8094086473},
{"learn":[0.3692592727],"iteration":104,"passed_time":0.2870954794,"remaining_time":0.8066015851},
{"learn":[0.3673754317],"iteration":105,"passed_time":0.2893662381,"remaining_time":0.8025818303},
{"learn":[0.365756672],"iteration":106,"passed_time":0.2917304666,"remaining_time":0.7988507169},
{"learn":[0.3633308006],"iteration":107,"passed_time":0.2939029768,"remaining_time":0.794626567},
{"learn":[0.3611422422],"iteration":108,"passed_time":0.2959407414,"remaining_time":0.7900803278},
{"learn":[0.3588800934],"iteration":109,"passed_time":0.2979542979,"remaining_time":0.7855158762},
{"learn":[0.3577484691],"iteration":110,"passed_time":0.300157417,"remaining_time":0.7814909326},
{"learn":[0.3556207167],"iteration":111,"passed_time":0.3024073608,"remaining_time":0.7776189279},
{"learn":[0.3542557201],"iteration":112,"passed_time":0.3047060013,"remaining_time":0.7738993131},
{"learn":[0.3524130504],"iteration":113,"passed_time":0.3067897406,"remaining_time":0.7696654895},
{"learn":[0.3493143491],"iteration":114,"passed_time":0.3091043933,"remaining_time":0.7660413224},
{"learn":[0.3462942559],"iteration":115,"passed_time":0.3115459641,"remaining_time":0.7627504638},
{"learn":[0.3438207294],"iteration":116,"passed_time":0.3137702144,"remaining_time":0.7589484673},
{"learn":[0.3426879596],"iteration":117,"passed_time":0.3162274736,"remaining_time":0.7557300641},
{"learn":[0.3404764213],"iteration":118,"passed_time":0.3183924469,"remaining_time":0.7518342654},
{"learn":[0.3397501858],"iteration":119,"passed_time":0.3204698772,"remaining_time":0.7477630468},
{"learn":[0.3380209259],"iteration":120,"passed_time":0.3228972255,"remaining_time":0.7445316192},
{"learn":[0.3369034148],"iteration":121,"passed_time":0.3251267638,"remaining_time":0.7408626256},
{"learn":[0.3351775458],"iteration":122,"passed_time":0.3274011407,"remaining_time":0.737318016},
{"learn":[0.3336531339],"iteration":123,"passed_time":0.3297271216,"remaining_time":0.7339087546},
{"learn":[0.3326999182],"iteration":124,"passed_time":0.3323832055,"remaining_time":0.7312430522},
{"learn":[0.3317298629],"iteration":125,"passed_time":0.3360493377,"remaining_time":0.7307739565},
{"learn":[0.3296376685],"iteration":126,"passed_time":0.3385404135,"remaining_time":0.7277286054},
{"learn":[0.3276256859],"iteration":127,"passed_time":0.3410259487,"remaining_time":0.7246801409},
{"learn":[0.3259549409],"iteration":128,"passed_time":0.3431711912,"remaining_time":0.7209255257},
{"learn":[0.3245230439],"iteration":129,"passed_time":0.3454114481,"remaining_time":0.7173930076},
{"learn":[0.3231476915],"iteration":130,"passed_time":0.3475235325,"remaining_time":0.7136170247},
{"learn":[0.3224515382],"iteration":131,"passed_time":0.3496632443,"remaining_time":0.7099223446},
{"learn":[0.320104481],"iteration":132,"passed_time":0.3518320237,"remaining_time":0.7063094009},
{"learn":[0.318688828],"iteration":133,"passed_time":0.3539358966,"remaining_time":0.702589168},
{"learn":[0.3180098351],"iteration":134,"passed_time":0.3563306393,"remaining_time":0.6994638474},
{"learn":[0.3164406549],"iteration":135,"passed_time":0.3584809823,"remaining_time":0.6958748479},
{"learn":[0.3153891049],"iteration":136,"passed_time":0.3613817044,"remaining_time":0.6937473596},
{"learn":[0.3140540073],"iteration":137,"passed_time":0.3638209331,"remaining_time":0.6907324961},
{"learn":[0.3128426524],"iteration":138,"passed_time":0.3661521321,"remaining_time":0.6875230681},
{"learn":[0.311498757],"iteration":139,"passed_time":0.3689558131,"remaining_time":0.6852036528},
{"learn":[0.3101245502],"iteration":140,"passed_time":0.3712758473,"remaining_time":0.6819889677},
{"learn":[0.3088488381],"iteration":141,"passed_time":0.3735613362,"remaining_time":0.6787241179},
{"learn":[0.3079274917],"iteration":142,"passed_time":0.3760054511,"remaining_time":0.6757580484},
{"learn":[0.3058384362],"iteration":143,"passed_time":0.3784789052,"remaining_time":0.6728513871},
{"learn":[0.3044367819],"iteration":144,"passed_time":0.3806432297,"remaining_time":0.6694070591},
{"learn":[0.3027855342],"iteration":145,"passed_time":0.3827442632,"remaining_time":0.6658701565},
{"learn":[0.3018727795],"iteration":146,"passed_time":0.3848018396,"remaining_time":0.6622779961},
{"learn":[0.2998246202],"iteration":147,"passed_time":0.387182289,"remaining_time":0.6592563298},
{"learn":[0.2976251103],"iteration":148,"passed_time":0.3894188349,"remaining_time":0.6560008562},
{"learn":[0.2965252408],"iteration":149,"passed_time":0.3916226857,"remaining_time":0.6527044761},
{"learn":[0.2950957037],"iteration":150,"passed_time":0.3940374369,"remaining_time":0.6497703429},
{"learn":[0.2943600975],"iteration":151,"passed_time":0.3963907812,"remaining_time":0.6467428535},
{"learn":[0.2936644254],"iteration":152,"passed_time":0.3986801217,"remaining_time":0.6436208501},
{"learn":[0.292024954],"iteration":153,"passed_time":0.4007448722,"remaining_time":0.6401508997},
{"learn":[0.2906996394],"iteration":154,"passed_time":0.402890514,"remaining_time":0.6368269415},
{"learn":[0.2893567979],"iteration":155,"passed_time":0.4049854033,"remaining_time":0.6334387077},
{"learn":[0.2882843071],"iteration":156,"passed_time":0.4075140481,"remaining_time":0.6307383038},
{"learn":[0.2874264703],"iteration":157,"passed_time":0.4102487692,"remaining_time":0.6283557098},
{"learn":[0.2857994168],"iteration":158,"passed_time":0.4127386738,"remaining_time":0.6255976124},
{"learn":[0.2836230929],"iteration":159,"passed_time":0.4151797949,"remaining_time":0.6227696923},
{"learn":[0.2810591134],"iteration":160,"passed_time":0.4176736582,"remaining_time":0.6200248714},
{"learn":[0.2800830783],"iteration":161,"passed_time":0.4204329507,"remaining_time":0.6176731003},
{"learn":[0.2786032743],"iteration":162,"passed_time":0.4233830954,"remaining_time":0.6155938259},
{"learn":[0.2773525582],"iteration":163,"passed_time":0.42657805,"remaining_time":0.6138562183},
{"learn":[0.2757946732],"iteration":164,"passed_time":0.4292775498,"remaining_time":0.6113952982},
{"learn":[0.2746485921],"iteration":165,"passed_time":0.4318202373,"remaining_time":0.608710455},
{"learn":[0.2738366691],"iteration":166,"passed_time":0.435188632,"remaining_time":0.6071793488},
{"learn":[0.2725149057],"iteration":167,"passed_time":0.4378972394,"remaining_time":0.6047152354},
{"learn":[0.2708970853],"iteration":168,"passed_time":0.4405006354,"remaining_time":0.6021044189},
{"learn":[0.2698830407],"iteration":169,"passed_time":0.4431231466,"remaining_time":0.5995195513},
{"learn":[0.2692675116],"iteration":170,"passed_time":0.4457446244,"remaining_time":0.5969328596},
{"learn":[0.2687280472],"iteration":171,"passed_time":0.4483160144,"remaining_time":0.5942793679},
{"learn":[0.2668031953],"iteration":172,"passed_time":0.4508149902,"remaining_time":0.591531808},
{"learn":[0.2660559732],"iteration":173,"passed_time":0.4534582059,"remaining_time":0.5889744514},
{"learn":[0.2647990941],"iteration":174,"passed_time":0.456086536,"remaining_time":0.5863969748},
{"learn":[0.2637368675],"iteration":175,"passed_time":0.458598292,"remaining_time":0.5836705534},
{"learn":[0.2601604472],"iteration":176,"passed_time":0.4612020742,"remaining_time":0.5810625002},
{"learn":[0.2590323055],"iteration":177,"passed_time":0.4637211593,"remaining_time":0.5783488616},
{"learn":[0.25644695],"iteration":178,"passed_time":0.4663479203,"remaining_time":0.5757703373},
{"learn":[0.2552468903],"iteration":179,"passed_time":0.4693318664,"remaining_time":0.5736278367},
{"learn":[0.2537408302],"iteration":180,"passed_time":0.4720189706,"remaining_time":0.571116876},
{"learn":[0.2519631362],"iteration":181,"passed_time":0.4745152552,"remaining_time":0.5683754156},
{"learn":[0.2511357254],"iteration":182,"passed_time":0.4771020106,"remaining_time":0.5657439142},
{"learn":[0.2495515613],"iteration":183,"passed_time":0.4796530638,"remaining_time":0.563070988},
{"learn":[0.2485879211],"iteration":184,"passed_time":0.4824842864,"remaining_time":0.5607249815},
{"learn":[0.2471097896],"iteration":185,"passed_time":0.4857632245,"remaining_time":0.5588888712},
{"learn":[0.2450127381],"iteration":186,"passed_time":0.4885521357,"remaining_time":0.5564791706},
{"learn":[0.2442352046],"iteration":187,"passed_time":0.490956215,"remaining_time":0.5536314765},
{"learn":[0.2430375964],"iteration":188,"passed_time":0.4935319503,"remaining_time":0.5509801139},
{"learn":[0.2422180441],"iteration":189,"passed_time":0.4959787416,"remaining_time":0.5481870302},
{"learn":[0.2417098533],"iteration":190,"passed_time":0.4986086806,"remaining_time":0.5455979804},
{"learn":[0.2410725815],"iteration":191,"passed_time":0.5009998406,"remaining_time":0.5427498273},
{"learn":[0.2394489875],"iteration":192,"passed_time":0.5033699974,"remaining_time":0.5398838833},
{"learn":[0.2387676806],"iteration":193,"passed_time":0.5055962761,"remaining_time":0.5368702725},
{"learn":[0.2372039991],"iteration":194,"passed_time":0.5081990297,"remaining_time":0.5342605184},
{"learn":[0.2353589695],"iteration":195,"passed_time":0.5105969484,"remaining_time":0.5314376402},
{"learn":[0.2334047457],"iteration":196,"passed_time":0.513677448,"remaining_time":0.5293224464},
{"learn":[0.2323707684],"iteration":197,"passed_time":0.5169273554,"remaining_time":0.5273703323},
{"learn":[0.2312365781],"iteration":198,"passed_time":0.5196254249,"remaining_time":0.524847791},
{"learn":[0.230735948],"iteration":199,"passed_time":0.5223452555,"remaining_time":0.5223452555},
{"learn":[0.2291260549],"iteration":200,"passed_time":0.5249041759,"remaining_time":0.5196812487},
{"learn":[0.2282734418],"iteration":201,"passed_time":0.5273932801,"remaining_time":0.5169498488},
{"learn":[0.2273690955],"iteration":202,"passed_time":0.5300772537,"remaining_time":0.5144099457},
{"learn":[0.226063072],"iteration":203,"passed_time":0.5322075901,"remaining_time":0.5113367043},
{"learn":[0.2253013243],"iteration":204,"passed_time":0.5342507921,"remaining_time":0.5081897779},
{"learn":[0.2246329163],"iteration":205,"passed_time":0.5372721079,"remaining_time":0.5059747035},
{"learn":[0.2234413567],"iteration":206,"passed_time":0.5400954245,"remaining_time":0.5035672315},
{"learn":[0.2223717298],"iteration":207,"passed_time":0.5429451118,"remaining_time":0.5011801032},
{"learn":[0.2214169333],"iteration":208,"passed_time":0.5454915862,"remaining_time":0.4985114496},
{"learn":[0.2208945147],"iteration":209,"passed_time":0.5476356998,"remaining_time":0.4954799189},
{"learn":[0.2199277815],"iteration":210,"passed_time":0.5498651917,"remaining_time":0.492533276},
{"learn":[0.2192214328],"iteration":211,"passed_time":0.5520081248,"remaining_time":0.489516639},
{"learn":[0.2185508024],"iteration":212,"passed_time":0.5540583021,"remaining_time":0.4864267723},
{"learn":[0.2175636555],"iteration":213,"passed_time":0.5571864994,"remaining_time":0.484283593},
{"learn":[0.2165801972],"iteration":214,"passed_time":0.5595199675,"remaining_time":0.4814474139},
{"learn":[0.2147751016],"iteration":215,"passed_time":0.5624201699,"remaining_time":0.4790986633},
{"learn":[0.2132467719],"iteration":216,"passed_time":0.5646138421,"remaining_time":0.4761490005},
{"learn":[0.2125639299],"iteration":217,"passed_time":0.5666977093,"remaining_time":0.4731146013},
{"learn":[0.2111288942],"iteration":218,"passed_time":0.5694069659,"remaining_time":0.4706057572},
{"learn":[0.2094897436],"iteration":219,"passed_time":0.5723565758,"remaining_time":0.4682917438},
{"learn":[0.2086788974],"iteration":220,"passed_time":0.5748234972,"remaining_time":0.4655810226},
{"learn":[0.2063402943],"iteration":221,"passed_time":0.5771172802,"remaining_time":0.4627336751},
{"learn":[0.2056934228],"iteration":222,"passed_time":0.5792292226,"remaining_time":0.4597469615},
{"learn":[0.2045278443],"iteration":223,"passed_time":0.5813768745,"remaining_time":0.4567961157},
{"learn":[0.203369941],"iteration":224,"passed_time":0.5836886046,"remaining_time":0.4539800258},
{"learn":[0.202667785],"iteration":225,"passed_time":0.586028888,"remaining_time":0.4511903828},
{"learn":[0.2014928129],"iteration":226,"passed_time":0.5885853911,"remaining_time":0.4485694831},
{"learn":[0.2008513713],"iteration":227,"passed_time":0.5918814679,"remaining_time":0.4465070723},
{"learn":[0.1989956651],"iteration":228,"passed_time":0.5941453268,"remaining_time":0.4436631043},
{"learn":[0.1981926316],"iteration":229,"passed_time":0.5963439104,"remaining_time":0.4407759338},
{"learn":[0.1967210298],"iteration":230,"passed_time":0.5985293963,"remaining_time":0.4378851428},
{"learn":[0.1960453361],"iteration":231,"passed_time":0.6012351107,"remaining_time":0.4353771491},
{"learn":[0.1951785639],"iteration":232,"passed_time":0.603750347,"remaining_time":0.4327309354},
{"learn":[0.1937018758],"iteration":233,"passed_time":0.6060884378,"remaining_time":0.4299601738},
{"learn":[0.1931872012],"iteration":234,"passed_time":0.608626331,"remaining_time":0.4273333813},
{"learn":[0.1927983314],"iteration":235,"passed_time":0.6110567307,"remaining_time":0.4246326433},
{"learn":[0.191579645],"iteration":236,"passed_time":0.6131986308,"remaining_time":0.4217357672},
{"learn":[0.1909583652],"iteration":237,"passed_time":0.6156422412,"remaining_time":0.4190506011},
{"learn":[0.1904672202],"iteration":238,"passed_time":0.6178165012,"remaining_time":0.4161860113},
{"learn":[0.1896681504],"iteration":239,"passed_time":0.6207988819,"remaining_time":0.4138659213},
{"learn":[0.1889212261],"iteration":240,"passed_time":0.6235653556,"remaining_time":0.4113978902},
{"learn":[0.1885260328],"iteration":241,"passed_time":0.6261002147,"remaining_time":0.4087761732},
{"learn":[0.18773119],"iteration":242,"passed_time":0.6292683628,"remaining_time":0.4065643332},
{"learn":[0.1872067324],"iteration":243,"passed_time":0.6323595907,"remaining_time":0.404295476},
{"learn":[0.1860332839],"iteration":244,"passed_time":0.6350810782,"remaining_time":0.4017859883},
{"learn":[0.1851623191],"iteration":245,"passed_time":0.6374286652,"remaining_time":0.3990407091},
{"learn":[0.1838546689],"iteration":246,"passed_time":0.6395631339,"remaining_time":0.3961666376},
{"learn":[0.1827774814],"iteration":247,"passed_time":0.6422511639,"remaining_time":0.3936378101},
{"learn":[0.182007795],"iteration":248,"passed_time":0.6447716698,"remaining_time":0.391006113},
{"learn":[0.1806459029],"iteration":249,"passed_time":0.6472049576,"remaining_time":0.3883229746},
{"learn":[0.1799047064],"iteration":250,"passed_time":0.6497146005,"remaining_time":0.3856871533},
{"learn":[0.1786031162],"iteration":251,"passed_time":0.6519260714,"remaining_time":0.3828772165},
{"learn":[0.1779223936],"iteration":252,"passed_time":0.6544064757,"remaining_time":0.3802282685},
{"learn":[0.1770513141],"iteration":253,"passed_time":0.6571892675,"remaining_time":0.3777544608},
{"learn":[0.1761805784],"iteration":254,"passed_time":0.65947666,"remaining_time":0.3749965322},
{"learn":[0.1744442619],"iteration":255,"passed_time":0.6624814402,"remaining_time":0.3726458101},
{"learn":[0.1737242123],"iteration":256,"passed_time":0.6647192147,"remaining_time":0.3698632206},
{"learn":[0.1725558845],"iteration":257,"passed_time":0.6671575747,"remaining_time":0.3671952543},
{"learn":[0.1711091183],"iteration":258,"passed_time":0.6696909682,"remaining_time":0.3645807974},
{"learn":[0.1706241135],"iteration":259,"passed_time":0.6721875247,"remaining_time":0.3619471287},
{"learn":[0.1702025496],"iteration":260,"passed_time":0.6754290017,"remaining_time":0.3597112308},
{"learn":[0.1694573436],"iteration":261,"passed_time":0.678412983,"remaining_time":0.3573320292},
{"learn":[0.1688186284],"iteration":262,"passed_time":0.6820334226,"remaining_time":0.3552797677},
{"learn":[0.1679957768],"iteration":263,"passed_time":0.6858047873,"remaining_time":0.3532933753},
{"learn":[0.1668070696],"iteration":264,"passed_time":0.6884821426,"remaining_time":0.3507361859},
{"learn":[0.1661217647],"iteration":265,"passed_time":0.6917182501,"remaining_time":0.3484595696},
{"learn":[0.1651741852],"iteration":266,"passed_time":0.6944036117,"remaining_time":0.3459014245},
{"learn":[0.1643359603],"iteration":267,"passed_time":0.6970645774,"remaining_time":0.3433303142},
{"learn":[0.1636582504],"iteration":268,"passed_time":0.6993427476,"remaining_time":0.3405721187},
{"learn":[0.1621614005],"iteration":269,"passed_time":0.7017795197,"remaining_time":0.3378938428},
{"learn":[0.1608452962],"iteration":270,"passed_time":0.7046529925,"remaining_time":0.3354252252},
{"learn":[0.1595531569],"iteration":271,"passed_time":0.7073107442,"remaining_time":0.3328521149},
{"learn":[0.1584139376],"iteration":272,"passed_time":0.709828074,"remaining_time":0.33021306},
{"learn":[0.1573928478],"iteration":273,"passed_time":0.7122336344,"remaining_time":0.3275234961},
{"learn":[0.1566518117],"iteration":274,"passed_time":0.7147004898,"remaining_time":0.324863859},
{"learn":[0.1559322089],"iteration":275,"passed_time":0.7179500026,"remaining_time":0.3225572475},
{"learn":[0.1552084478],"iteration":276,"passed_time":0.721562278,"remaining_time":0.3204049105},
{"learn":[0.1547148399],"iteration":277,"passed_time":0.7240831728,"remaining_time":0.317763119},
{"learn":[0.1541315008],"iteration":278,"passed_time":0.7275002994,"remaining_time":0.3155108825},
{"learn":[0.1536599907],"iteration":279,"passed_time":0.7300803896,"remaining_time":0.3128915956},
{"learn":[0.1524922815],"iteration":280,"passed_time":0.7333002862,"remaining_time":0.3105435376},
{"learn":[0.1522633425],"iteration":281,"passed_time":0.7366078,"remaining_time":0.3082259589},
{"learn":[0.1519711689],"iteration":282,"passed_time":0.7395799957,"remaining_time":0.3057627544},
{"learn":[0.1511712513],"iteration":283,"passed_time":0.7419742199,"remaining_time":0.3030598926},
{"learn":[0.1498972575],"iteration":284,"passed_time":0.7440816359,"remaining_time":0.3002434671},
{"learn":[0.1495169335],"iteration":285,"passed_time":0.7469840846,"remaining_time":0.2977489008},
{"learn":[0.1486771048],"iteration":286,"passed_time":0.749795616,"remaining_time":0.2952156955},
{"learn":[0.1472202806],"iteration":287,"passed_time":0.7532769705,"remaining_time":0.2929410441},
{"learn":[0.1464432054],"iteration":288,"passed_time":0.7557948471,"remaining_time":0.2902879863},
{"learn":[0.1456172494],"iteration":289,"passed_time":0.7581813188,"remaining_time":0.2875860175},
{"learn":[0.144755678],"iteration":290,"passed_time":0.7607411802,"remaining_time":0.2849511637},
{"learn":[0.1440672916],"iteration":291,"passed_time":0.7628947157,"remaining_time":0.2821665387},
{"learn":[0.1427802271],"iteration":292,"passed_time":0.7653890383,"remaining_time":0.2795106727},
{"learn":[0.1420113082],"iteration":293,"passed_time":0.7682755228,"remaining_time":0.2769972973},
{"learn":[0.1411633346],"iteration":294,"passed_time":0.7707744386,"remaining_time":0.2743434442},
{"learn":[0.1404995432],"iteration":295,"passed_time":0.7730493531,"remaining_time":0.2716119349},
{"learn":[0.1398651009],"iteration":296,"passed_time":0.7751565597,"remaining_time":0.2688253389},
{"learn":[0.1395162224],"iteration":297,"passed_time":0.7777950899,"remaining_time":0.266225165},
{"learn":[0.1390406226],"iteration":298,"passed_time":0.7804428141,"remaining_time":0.2636278402},
{"learn":[0.1383084073],"iteration":299,"passed_time":0.7829675749,"remaining_time":0.2609891916},
{"learn":[0.1378606445],"iteration":300,"passed_time":0.7856287901,"remaining_time":0.2583961801},
{"learn":[0.1372876727],"iteration":301,"passed_time":0.7878635591,"remaining_time":0.2556643338},
{"learn":[0.1367583006],"iteration":302,"passed_time":0.7899810274,"remaining_time":0.2528982167},
{"learn":[0.136465749],"iteration":303,"passed_time":0.7926866814,"remaining_time":0.2503221099},
{"learn":[0.1356806434],"iteration":304,"passed_time":0.7950434676,"remaining_time":0.2476364899},
{"learn":[0.1353114886],"iteration":305,"passed_time":0.7970975634,"remaining_time":0.2448600358},
{"learn":[0.134844217],"iteration":306,"passed_time":0.8000086012,"remaining_time":0.2423478825},
{"learn":[0.1339778229],"iteration":307,"passed_time":0.8022120766,"remaining_time":0.2396217891},
{"learn":[0.1331882497],"iteration":308,"passed_time":0.8043813976,"remaining_time":0.23688902},
{"learn":[0.1325046173],"iteration":309,"passed_time":0.8066108971,"remaining_time":0.2341773572},
{"learn":[0.1319862884],"iteration":310,"passed_time":0.8091455883,"remaining_time":0.231556133},
{"learn":[0.1314933678],"iteration":311,"passed_time":0.8117209786,"remaining_time":0.2289469427},
{"learn":[0.131227267],"iteration":312,"passed_time":0.8145867193,"remaining_time":0.2264186728},
{"learn":[0.1307845333],"iteration":313,"passed_time":0.8173008602,"remaining_time":0.2238467324},
{"learn":[0.130168248],"iteration":314,"passed_time":0.8194081139,"remaining_time":0.221110126},
{"learn":[0.1296041313],"iteration":315,"passed_time":0.8216477655,"remaining_time":0.2184126972},
{"learn":[0.1291602634],"iteration":316,"passed_time":0.8241891035,"remaining_time":0.215797147},
{"learn":[0.128425734],"iteration":317,"passed_time":0.8270739941,"remaining_time":0.2132706526},
{"learn":[0.1279108647],"iteration":318,"passed_time":0.829838112,"remaining_time":0.2107112447},
{"learn":[0.1272250443],"iteration":319,"passed_time":0.8326480824,"remaining_time":0.2081620206},
{"learn":[0.1267491124],"iteration":320,"passed_time":0.8351663108,"remaining_time":0.2055393724},
{"learn":[0.125879946],"iteration":321,"passed_time":0.8377523359,"remaining_time":0.2029337956},
{"learn":[0.1252896648],"iteration":322,"passed_time":0.8403981644,"remaining_time":0.2003425965},
{"learn":[0.1248404587],"iteration":323,"passed_time":0.8427750188,"remaining_time":0.1976879674},
{"learn":[0.1243146493],"iteration":324,"passed_time":0.8450790455,"remaining_time":0.1950182413},
{"learn":[0.1235437715],"iteration":325,"passed_time":0.8475629389,"remaining_time":0.1923915874},
{"learn":[0.1229031203],"iteration":326,"passed_time":0.8496632477,"remaining_time":0.1896801746},
{"learn":[0.1223795677],"iteration":327,"passed_time":0.8517502377,"remaining_time":0.1869695644},
{"learn":[0.121612516],"iteration":328,"passed_time":0.8541332103,"remaining_time":0.1843266199},
{"learn":[0.120893864],"iteration":329,"passed_time":0.8566729293,"remaining_time":0.1817185001},
{"learn":[0.1204689207],"iteration":330,"passed_time":0.8591510518,"remaining_time":0.1790979534},
{"learn":[0.1199460898],"iteration":331,"passed_time":0.8614231784,"remaining_time":0.1764360727},
{"learn":[0.1192161999],"iteration":332,"passed_time":0.8639908891,"remaining_time":0.1738360047},
{"learn":[0.1184199023],"iteration":333,"passed_time":0.8661727536,"remaining_time":0.1711598854},
{"learn":[0.1179790472],"iteration":334,"passed_time":0.8687250928,"remaining_time":0.1685586001},
{"learn":[0.1174262142],"iteration":335,"passed_time":0.871125875,"remaining_time":0.1659287381},
{"learn":[0.1170682628],"iteration":336,"passed_time":0.873247061,"remaining_time":0.1632479669},
{"learn":[0.1168278225],"iteration":337,"passed_time":0.8753247951,"remaining_time":0.1605625364},
{"learn":[0.1162654814],"iteration":338,"passed_time":0.8775762811,"remaining_time":0.1579119562},
{"learn":[0.1153783184],"iteration":339,"passed_time":0.8801601707,"remaining_time":0.1553223831},
{"learn":[0.1151741921],"iteration":340,"passed_time":0.8825417753,"remaining_time":0.1526978438},
{"learn":[0.114607452],"iteration":341,"passed_time":0.884656221,"remaining_time":0.1500294176},
{"learn":[0.1142166004],"iteration":342,"passed_time":0.886768333,"remaining_time":0.1473638338},
{"learn":[0.1138984914],"iteration":343,"passed_time":0.888866838,"remaining_time":0.1446992527},
{"learn":[0.1137181583],"iteration":344,"passed_time":0.891014328,"remaining_time":0.1420457624},
{"learn":[0.1134789666],"iteration":345,"passed_time":0.8935752016,"remaining_time":0.1394597135},
{"learn":[0.1125567496],"iteration":346,"passed_time":0.8962268933,"remaining_time":0.1368876811},
{"learn":[0.1123077634],"iteration":347,"passed_time":0.8984632962,"remaining_time":0.1342531362},
{"learn":[0.1118931873],"iteration":348,"passed_time":0.900540637,"remaining_time":0.1315976289},
{"learn":[0.1114883256],"iteration":349,"passed_time":0.9029531235,"remaining_time":0.1289933034},
{"learn":[0.1112245846],"iteration":350,"passed_time":0.9051449692,"remaining_time":0.1263592692},
{"learn":[0.1108392431],"iteration":351,"passed_time":0.9071853533,"remaining_time":0.1237070936},
{"learn":[0.1104672587],"iteration":352,"passed_time":0.9099354286,"remaining_time":0.1211528758},
{"learn":[0.1101720723],"iteration":353,"passed_time":0.9130785472,"remaining_time":0.1186486248},
{"learn":[0.1100302756],"iteration":354,"passed_time":0.9155708579,"remaining_time":0.1160582778},
{"learn":[0.1092149389],"iteration":355,"passed_time":0.9179186056,"remaining_time":0.1134506142},
{"learn":[0.1089137956],"iteration":356,"passed_time":0.9201196792,"remaining_time":0.1108267401},
{"learn":[0.1086165128],"iteration":357,"passed_time":0.9231133698,"remaining_time":0.1082982166},
{"learn":[0.1079750941],"iteration":358,"passed_time":0.9256342834,"remaining_time":0.1057131076},
{"learn":[0.1071574777],"iteration":359,"passed_time":0.9283424675,"remaining_time":0.1031491631},
{"learn":[0.1066969076],"iteration":360,"passed_time":0.9307630907,"remaining_time":0.1005533533},
{"learn":[0.1058088167],"iteration":361,"passed_time":0.9330149318,"remaining_time":0.09794079394},
{"learn":[0.1052043765],"iteration":362,"passed_time":0.9350654165,"remaining_time":0.0953096981},
{"learn":[0.104700493],"iteration":363,"passed_time":0.9371929095,"remaining_time":0.09268940863},
{"learn":[0.104121507],"iteration":364,"passed_time":0.9394736537,"remaining_time":0.09008651474},
{"learn":[0.103631668],"iteration":365,"passed_time":0.9422198457,"remaining_time":0.08752861955},
{"learn":[0.1031243364],"iteration":366,"passed_time":0.9451868686,"remaining_time":0.08498955495},
{"learn":[0.102520091],"iteration":367,"passed_time":0.9476116225,"remaining_time":0.08240101065},
{"learn":[0.1021186888],"iteration":368,"passed_time":0.9497681821,"remaining_time":0.07979082289},
{"learn":[0.1018174882],"iteration":369,"passed_time":0.9521597671,"remaining_time":0.07720214328},
{"learn":[0.1013872066],"iteration":370,"passed_time":0.9543452686,"remaining_time":0.07459841722},
{"learn":[0.101152093],"iteration":371,"passed_time":0.9564354052,"remaining_time":0.07198976168},
{"learn":[0.1009074256],"iteration":372,"passed_time":0.9600863106,"remaining_time":0.06949686431},
{"learn":[0.1007053154],"iteration":373,"passed_time":0.9622478556,"remaining_time":0.06689423595},
{"learn":[0.1003922698],"iteration":374,"passed_time":0.9647044812,"remaining_time":0.06431363208},
{"learn":[0.09998538044],"iteration":375,"passed_time":0.9669476863,"remaining_time":0.06172006508},
{"learn":[0.09951145321],"iteration":376,"passed_time":0.9692113158,"remaining_time":0.05912960282},
{"learn":[0.09907223627],"iteration":377,"passed_time":0.971455916,"remaining_time":0.05653976231},
{"learn":[0.09871846621],"iteration":378,"passed_time":0.9743481913,"remaining_time":0.05398763065},
{"learn":[0.09837610588],"iteration":379,"passed_time":0.9766119875,"remaining_time":0.05140063092},
{"learn":[0.09788875276],"iteration":380,"passed_time":0.9789065277,"remaining_time":0.04881686096},
{"learn":[0.09763225171],"iteration":381,"passed_time":0.9810039657,"remaining_time":0.04622531776},
{"learn":[0.09737971429],"iteration":382,"passed_time":0.9831854166,"remaining_time":0.04364008376},
{"learn":[0.09699368543],"iteration":383,"passed_time":0.9858539536,"remaining_time":0.04107724807},
{"learn":[0.09615039715],"iteration":384,"passed_time":0.9881332335,"remaining_time":0.03849869741},
{"learn":[0.09601236933],"iteration":385,"passed_time":0.9909113205,"remaining_time":0.03593978883},
{"learn":[0.09563285867],"iteration":386,"passed_time":0.9934506025,"remaining_time":0.03337172567},
{"learn":[0.09544305752],"iteration":387,"passed_time":0.9957420742,"remaining_time":0.03079614662},
{"learn":[0.09518618418],"iteration":388,"passed_time":0.9979036307,"remaining_time":0.0282183546},
{"learn":[0.09487696473],"iteration":389,"passed_time":1.000231882,"remaining_time":0.02564697132},
{"learn":[0.09458712806],"iteration":390,"passed_time":1.00224533,"remaining_time":0.0230695856},
{"learn":[0.09410545688],"iteration":391,"passed_time":1.005014692,"remaining_time":0.02051050392},
{"learn":[0.09369755366],"iteration":392,"passed_time":1.007884339,"remaining_time":0.01795213835},
{"learn":[0.0935120598],"iteration":393,"passed_time":1.010401322,"remaining_time":0.01538682216},
{"learn":[0.09340154818],"iteration":394,"passed_time":1.012835855,"remaining_time":0.01282070703},
{"learn":[0.09306986442],"iteration":395,"passed_time":1.015375634,"remaining_time":0.01025631954},
{"learn":[0.09299273425],"iteration":396,"passed_time":1.01773069,"remaining_time":0.007690660129},
{"learn":[0.09255183908],"iteration":397,"passed_time":1.01991255,"remaining_time":0.005125188694},
{"learn":[0.09243667078],"iteration":398,"passed_time":1.022751139,"remaining_time":0.002563286063},
{"learn":[0.09232220701],"iteration":399,"passed_time":1.024913063,"remaining_time":0}
]}